Workbook

Sheet Nivel Transaccion
A1: ID Transaccion | B1: Fecha Hora | C1: Sucursal | D1: Canal Venta | E1: ID Cliente | F1: Metodo Pago | G1: Vendedor | H1: Subtotal | I1: Descuento Total | J1: Impuestos (IVA 21%) | K1: Total Cobrado | L1: Costo Total ERP | M1: Margen Bruto
A2: TXN-20260801-001 | B2: 46235.651 | C2: SUC-003 E-Commerce | D2: E-Commerce | E2: CLI-1332 | F2: Tarjeta Crédito | G2: SISTEMA-WEB | H2: =SUMIF('Nivel Detalle de Item'!B:B, A2, 'Nivel Detalle de Item'!K:K)+SUMIF('Nivel Detalle de Item'!B:B, A2, 'Nivel Detalle de Item'!J:J) | I2: =SUMIF('Nivel Detalle de Item'!B:B, A2, 'Nivel Detalle de Item'!J:J) | J2: =(H2-I2)*0.21 | K2: =(H2-I2)+J2 | L2: =SUMIF('Nivel Detalle de Item'!B:B, A2, 'Nivel Detalle de Item'!L:L) | M2: =(H2-I2)-L2
A3: TXN-20260801-002 | B3: 46235.427 | C3: SUC-002 Norte | D3: Venta Telefónica | E3: CLI-5561 | F3: Tarjeta Crédito | G3: VEN-103 (Carlos Ruiz) | H3: =SUMIF('Nivel Detalle de Item'!B:B, A3, 'Nivel Detalle de Item'!K:K)+SUMIF('Nivel Detalle de Item'!B:B, A3, 'Nivel Detalle de Item'!J:J) | I3: =SUMIF('Nivel Detalle de Item'!B:B, A3, 'Nivel Detalle de Item'!J:J) | J3: =(H3-I3)*0.21 | K3: =(H3-I3)+J3 | L3: =SUMIF('Nivel Detalle de Item'!B:B, A3, 'Nivel Detalle de Item'!L:L) | M3: =(H3-I3)-L3
A4: TXN-20260801-003 | B4: 46235.635 | C4: SUC-002 Norte | D4: Tienda Física | E4: CLI-7747 | F4: Transferencia | G4: VEN-103 (Carlos Ruiz) | H4: =SUMIF('Nivel Detalle de Item'!B:B, A4, 'Nivel Detalle de Item'!K:K)+SUMIF('Nivel Detalle de Item'!B:B, A4, 'Nivel Detalle de Item'!J:J) | I4: =SUMIF('Nivel Detalle de Item'!B:B, A4, 'Nivel Detalle de Item'!J:J) | J4: =(H4-I4)*0.21 | K4: =(H4-I4)+J4 | L4: =SUMIF('Nivel Detalle de Item'!B:B, A4, 'Nivel Detalle de Item'!L:L) | M4: =(H4-I4)-L4
A5: TXN-20260801-004 | B5: 46235.673 | C5: SUC-002 Norte | D5: Venta Telefónica | E5: CLI-9550 | F5: Efectivo | G5: VEN-103 (Carlos Ruiz) | H5: =SUMIF('Nivel Detalle de Item'!B:B, A5, 'Nivel Detalle de Item'!K:K)+SUMIF('Nivel Detalle de Item'!B:B, A5, 'Nivel Detalle de Item'!J:J) | I5: =SUMIF('Nivel Detalle de Item'!B:B, A5, 'Nivel Detalle de Item'!J:J) | J5: =(H5-I5)*0.21 | K5: =(H5-I5)+J5 | L5: =SUMIF('Nivel Detalle de Item'!B:B, A5, 'Nivel Detalle de Item'!L:L) | M5: =(H5-I5)-L5
A6: TXN-20260801-005 | B6: 46235.529 | C6: SUC-002 Norte | D6: Tienda Física | E6: CLI-6704 | F6: Tarjeta Débito | G6: VEN-101 (Juan Pérez) | H6: =SUMIF('Nivel Detalle de Item'!B:B, A6, 'Nivel Detalle de Item'!K:K)+SUMIF('Nivel Detalle de Item'!B:B, A6, 'Nivel Detalle de Item'!J:J) | I6: =SUMIF('Nivel Detalle de Item'!B:B, A6, 'Nivel Detalle de Item'!J:J) | J6: =(H6-I6)*0.21 | K6: =(H6-I6)+J6 | L6: =SUMIF('Nivel Detalle de Item'!B:B, A6, 'Nivel Detalle de Item'!L:L) | M6: =(H6-I6)-L6
A7: TXN-20260801-006 | B7: 46235.829 | C7: SUC-003 E-Commerce | D7: E-Commerce | E7: CLI-6130 | F7: Transferencia | G7: SISTEMA-WEB | H7: =SUMIF('Nivel Detalle de Item'!B:B, A7, 'Nivel Detalle de Item'!K:K)+SUMIF('Nivel Detalle de Item'!B:B, A7, 'Nivel Detalle de Item'!J:J) | I7: =SUMIF('Nivel Detalle de Item'!B:B, A7, 'Nivel Detalle de Item'!J:J) | J7: =(H7-I7)*0.21 | K7: =(H7-I7)+J7 | L7: =SUMIF('Nivel Detalle de Item'!B:B, A7, 'Nivel Detalle de Item'!L:L) | M7: =(H7-I7)-L7
A8: TXN-20260801-007 | B8: 46235.424 | C8: SUC-002 Norte | D8: Venta Telefónica | E8: CLI-3321 | F8: Efectivo | G8: VEN-102 (María Gómez) | H8: =SUMIF('Nivel Detalle de Item'!B:B, A8, 'Nivel Detalle de Item'!K:K)+SUMIF('Nivel Detalle de Item'!B:B, A8, 'Nivel Detalle de Item'!J:J) | I8: =SUMIF('Nivel Detalle de Item'!B:B, A8, 'Nivel Detalle de Item'!J:J) | J8: =(H8-I8)*0.21 | K8: =(H8-I8)+J8 | L8: =SUMIF('Nivel Detalle de Item'!B:B, A8, 'Nivel Detalle de Item'!L:L) | M8: =(H8-I8)-L8
A9: TXN-20260801-008 | B9: 46235.613 | C9: SUC-003 E-Commerce | D9: E-Commerce | E9: CLI-5594 | F9: Transferencia | G9: SISTEMA-WEB | H9: =SUMIF('Nivel Detalle de Item'!B:B, A9, 'Nivel Detalle de Item'!K:K)+SUMIF('Nivel Detalle de Item'!B:B, A9, 'Nivel Detalle de Item'!J:J) | I9: =SUMIF('Nivel Detalle de Item'!B:B, A9, 'Nivel Detalle de Item'!J:J) | J9: =(H9-I9)*0.21 | K9: =(H9-I9)+J9 | L9: =SUMIF('Nivel Detalle de Item'!B:B, A9, 'Nivel Detalle de Item'!L:L) | M9: =(H9-I9)-L9
A10: TXN-20260801-009 | B10: 46235.41 | C10: SUC-003 E-Commerce | D10: E-Commerce | E10: CLI-6724 | F10: Transferencia | G10: SISTEMA-WEB | H10: =SUMIF('Nivel Detalle de Item'!B:B, A10, 'Nivel Detalle de Item'!K:K)+SUMIF('Nivel Detalle de Item'!B:B, A10, 'Nivel Detalle de Item'!J:J) | I10: =SUMIF('Nivel Detalle de Item'!B:B, A10, 'Nivel Detalle de Item'!J:J) | J10: =(H10-I10)*0.21 | K10: =(H10-I10)+J10 | L10: =SUMIF('Nivel Detalle de Item'!B:B, A10, 'Nivel Detalle de Item'!L:L) | M10: =(H10-I10)-L10
A11: TXN-20260801-010 | B11: 46235.63 | C11: SUC-001 Centro | D11: Tienda Física | E11: CLI-3810 | F11: Tarjeta Crédito | G11: VEN-101 (Juan Pérez) | H11: =SUMIF('Nivel Detalle de Item'!B:B, A11, 'Nivel Detalle de Item'!K:K)+SUMIF('Nivel Detalle de Item'!B:B, A11, 'Nivel Detalle de Item'!J:J) | I11: =SUMIF('Nivel Detalle de Item'!B:B, A11, 'Nivel Detalle de Item'!J:J) | J11: =(H11-I11)*0.21 | K11: =(H11-I11)+J11 | L11: =SUMIF('Nivel Detalle de Item'!B:B, A11, 'Nivel Detalle de Item'!L:L) | M11: =(H11-I11)-L11
A12: TXN-20260801-011 | B12: 46235.74 | C12: SUC-003 E-Commerce | D12: E-Commerce | E12: CLI-9996 | F12: Tarjeta Crédito | G12: SISTEMA-WEB | H12: =SUMIF('Nivel Detalle de Item'!B:B, A12, 'Nivel Detalle de Item'!K:K)+SUMIF('Nivel Detalle de Item'!B:B, A12, 'Nivel Detalle de Item'!J:J) | I12: =SUMIF('Nivel Detalle de Item'!B:B, A12, 'Nivel Detalle de Item'!J:J) | J12: =(H12-I12)*0.21 | K12: =(H12-I12)+J12 | L12: =SUMIF('Nivel Detalle de Item'!B:B, A12, 'Nivel Detalle de Item'!L:L) | M12: =(H12-I12)-L12
A13: TXN-20260801-012 | B13: 46235.785 | C13: SUC-001 Centro | D13: Tienda Física | E13: CLI-2673 | F13: Transferencia | G13: VEN-101 (Juan Pérez) | H13: =SUMIF('Nivel Detalle de Item'!B:B, A13, 'Nivel Detalle de Item'!K:K)+SUMIF('Nivel Detalle de Item'!B:B, A13, 'Nivel Detalle de Item'!J:J) | I13: =SUMIF('Nivel Detalle de Item'!B:B, A13, 'Nivel Detalle de Item'!J:J) | J13: =(H13-I13)*0.21 | K13: =(H13-I13)+J13 | L13: =SUMIF('Nivel Detalle de Item'!B:B, A13, 'Nivel Detalle de Item'!L:L) | M13: =(H13-I13)-L13
... A38: TXN-20260801-037 | B38: 46235.391 | C38: SUC-003 E-Commerce | D38: E-Commerce | E38: CLI-8145 | F38: Transferencia | G38: SISTEMA-WEB | H38: =SUMIF('Nivel Detalle de Item'!B:B, A38, 'Nivel Detalle de Item'!K:K)+SUMIF('Nivel Detalle de Item'!B:B, A38, 'Nivel Detalle de Item'!J:J) | I38: =SUMIF('Nivel Detalle de Item'!B:B, A38, 'Nivel Detalle de Item'!J:J) | J38: =(H38-I38)*0.21 | K38: =(H38-I38)+J38 | L38: =SUMIF('Nivel Detalle de Item'!B:B, A38, 'Nivel Detalle de Item'!L:L) | M38: =(H38-I38)-L38

Sheet Nivel Detalle de Item
A1: ID Linea | B1: ID Transaccion | C1: Nro Linea | D1: SKU | E1: Producto | F1: Categoria | G1: Cantidad | H1: Precio Unitario | I1: Costo Unitario | J1: Descuento Linea | K1: Total Linea | L1: Costo Total Linea | M1: Margen Bruto Linea
A2: 1 | B2: TXN-20260801-001 | C2: 1 | D2: PROD-102 | E2: Monitor 27 UHD | F2: Tecnología | G2: 3 | H2: 280000 | I2: 190000 | J2: 0 | K2: =(G2*H2)-J2 | L2: =G2*I2 | M2: =K2-L2
A3: 2 | B3: TXN-20260801-001 | C3: 2 | D3: PROD-101 | E3: Notebook Pro 15 | F3: Tecnología | G3: 3 | H3: 850000 | I3: 620000 | J3: 0 | K3: =(G3*H3)-J3 | L3: =G3*I3 | M3: =K3-L3
A4: 3 | B4: TXN-20260801-001 | C4: 3 | D4: PROD-101 | E4: Notebook Pro 15 | F4: Tecnología | G4: 3 | H4: 850000 | I4: 620000 | J4: 255000 | K4: =(G4*H4)-J4 | L4: =G4*I4 | M4: =K4-L4
A5: 4 | B5: TXN-20260801-001 | C5: 4 | D5: PROD-107 | E5: Escritorio Ajustable | F5: Muebles | G5: 2 | H5: 240000 | I5: 150000 | J5: 0 | K5: =(G5*H5)-J5 | L5: =G5*I5 | M5: =K5-L5
A6: 5 | B6: TXN-20260801-002 | C6: 1 | D6: PROD-108 | E6: Webcam 4K Ultra | F6: Tecnología | G6: 3 | H6: 75000 | I6: 42000 | J6: 11250 | K6: =(G6*H6)-J6 | L6: =G6*I6 | M6: =K6-L6
A7: 6 | B7: TXN-20260801-002 | C7: 2 | D7: PROD-106 | E7: Silla Ergonómica Oficina | F7: Muebles | G7: 2 | H7: 185000 | I7: 115000 | J7: 37000 | K7: =(G7*H7)-J7 | L7: =G7*I7 | M7: =K7-L7
A8: 7 | B8: TXN-20260801-003 | C8: 1 | D8: PROD-106 | E8: Silla Ergonómica Oficina | F8: Muebles | G8: 3 | H8: 185000 | I8: 115000 | J8: 55500 | K8: =(G8*H8)-J8 | L8: =G8*I8 | M8: =K8-L8
A9: 8 | B9: TXN-20260801-004 | C9: 1 | D9: PROD-102 | E9: Monitor 27 UHD | F9: Tecnología | G9: 2 | H9: 280000 | I9: 190000 | J9: 0 | K9: =(G9*H9)-J9 | L9: =G9*I9 | M9: =K9-L9
A10: 9 | B10: TXN-20260801-005 | C10: 1 | D10: PROD-108 | E10: Webcam 4K Ultra | F10: Tecnología | G10: 2 | H10: 75000 | I10: 42000 | J10: 0 | K10: =(G10*H10)-J10 | L10: =G10*I10 | M10: =K10-L10
A11: 10 | B11: TXN-20260801-006 | C11: 1 | D11: PROD-105 | E11: Auriculares Bluetooth | F11: Audio | G11: 3 | H11: 65000 | I11: 35000 | J11: 9750 | K11: =(G11*H11)-J11 | L11: =G11*I11 | M11: =K11-L11
A12: 11 | B12: TXN-20260801-006 | C12: 2 | D12: PROD-106 | E12: Silla Ergonómica Oficina | F12: Muebles | G12: 3 | H12: 185000 | I12: 115000 | J12: 27750 | K12: =(G12*H12)-J12 | L12: =G12*I12 | M12: =K12-L12
A13: 12 | B13: TXN-20260801-007 | C13: 1 | D13: PROD-104 | E13: Mouse Inalámbrico | F13: Accesorios | G13: 2 | H13: 25000 | I13: 11000 | J13: 0 | K13: =(G13*H13)-J13 | L13: =G13*I13 | M13: =K13-L13
... A94: 93 | B94: TXN-20260801-037 | C94: 2 | D94: PROD-101 | E94: Notebook Pro 15 | F94: Tecnología | G94: 1 | H94: 850000 | I94: 620000 | J94: 0 | K94: =(G94*H94)-J94 | L94: =G94*I94 | M94: =K94-L94
