Workbook

Sheet Fact_Ventas_Detalle
A1: ID Linea | B1: ID Transaccion | C1: Nro Linea | D1: SKU | E1: Producto | F1: Categoria | G1: Cantidad | H1: Precio Unitario | I1: Costo Unitario | J1: Descuento Linea | K1: Total
A2: 1 | B2: TXN-20260731-001 | C2: 1 | D2: PROD-102 | E2: Monitor 27 UHD | F2: Tecnología | G2: 3 | H2: 280000 | I2: 190000 | J2: 0 | K2: =(Fact_Ventas_Detalle[[#This Row],[Cantidad]]*Fact_Ventas_Detalle[[#This Row],[Precio Unitario]])-Fact_Ventas_Detalle[[#This Row],[Descuento Linea]] -> 840000
A3: 1 | B3: TXN-20260801-001 | C3: 1 | D3: PROD-102 | E3: Monitor 27 UHD | F3: Tecnología | G3: 3 | H3: 280000 | I3: 190000 | J3: 0 | K3: =(Fact_Ventas_Detalle[[#This Row],[Cantidad]]*Fact_Ventas_Detalle[[#This Row],[Precio Unitario]])-Fact_Ventas_Detalle[[#This Row],[Descuento Linea]] -> 840000
A4: 1 | B4: TXN-20260802-001 | C4: 1 | D4: PROD-105 | E4: Auriculares Bluetooth | F4: Audio | G4: 3 | H4: 65000 | I4: 35000 | J4: 0 | K4: =(Fact_Ventas_Detalle[[#This Row],[Cantidad]]*Fact_Ventas_Detalle[[#This Row],[Precio Unitario]])-Fact_Ventas_Detalle[[#This Row],[Descuento Linea]] -> 195000
A5: 1 | B5: TXN-20260804-001 | C5: 1 | D5: PROD-108 | E5: Webcam 4K Ultra | F5: Tecnología | G5: 3 | H5: 75000 | I5: 42000 | J5: 0 | K5: =(Fact_Ventas_Detalle[[#This Row],[Cantidad]]*Fact_Ventas_Detalle[[#This Row],[Precio Unitario]])-Fact_Ventas_Detalle[[#This Row],[Descuento Linea]] -> 225000
A6: 1 | B6: TXN-20260806-001 | C6: 1 | D6: PROD-103 | E6: Teclado Mecánico RGB | F6: Accesorios | G6: 3 | H6: 45000 | I6: 22000 | J6: 0 | K6: =(Fact_Ventas_Detalle[[#This Row],[Cantidad]]*Fact_Ventas_Detalle[[#This Row],[Precio Unitario]])-Fact_Ventas_Detalle[[#This Row],[Descuento Linea]] -> 135000
A7: 1 | B7: TXN-20260803-001 | C7: 1 | D7: PROD-102 | E7: Monitor 27 UHD | F7: Tecnología | G7: 1 | H7: 280000 | I7: 190000 | J7: 0 | K7: =(Fact_Ventas_Detalle[[#This Row],[Cantidad]]*Fact_Ventas_Detalle[[#This Row],[Precio Unitario]])-Fact_Ventas_Detalle[[#This Row],[Descuento Linea]] -> 280000
A8: 1 | B8: TXN-20260807-001 | C8: 1 | D8: PROD-108 | E8: Webcam 4K Ultra | F8: Tecnología | G8: 1 | H8: 75000 | I8: 42000 | J8: 0 | K8: =(Fact_Ventas_Detalle[[#This Row],[Cantidad]]*Fact_Ventas_Detalle[[#This Row],[Precio Unitario]])-Fact_Ventas_Detalle[[#This Row],[Descuento Linea]] -> 75000
A9: 1 | B9: TXN-20260727-001 | C9: 1 | D9: PROD-102 | E9: Monitor 27 UHD | F9: Tecnología | G9: 3 | H9: 280000 | I9: 190000 | J9: 84000 | K9: =(Fact_Ventas_Detalle[[#This Row],[Cantidad]]*Fact_Ventas_Detalle[[#This Row],[Precio Unitario]])-Fact_Ventas_Detalle[[#This Row],[Descuento Linea]] -> 756000
A10: 1 | B10: TXN-20260728-001 | C10: 1 | D10: PROD-102 | E10: Monitor 27 UHD | F10: Tecnología | G10: 3 | H10: 280000 | I10: 190000 | J10: 84000 | K10: =(Fact_Ventas_Detalle[[#This Row],[Cantidad]]*Fact_Ventas_Detalle[[#This Row],[Precio Unitario]])-Fact_Ventas_Detalle[[#This Row],[Descuento Linea]] -> 756000
A11: 1 | B11: TXN-20260805-001 | C11: 1 | D11: PROD-107 | E11: Escritorio Ajustable | F11: Muebles | G11: 3 | H11: 240000 | I11: 150000 | J11: 72000 | K11: =(Fact_Ventas_Detalle[[#This Row],[Cantidad]]*Fact_Ventas_Detalle[[#This Row],[Precio Unitario]])-Fact_Ventas_Detalle[[#This Row],[Descuento Linea]] -> 648000
A12: 1 | B12: TXN-20260729-001 | C12: 1 | D12: PROD-101 | E12: Notebook Pro 15 | F12: Tecnología | G12: 1 | H12: 850000 | I12: 620000 | J12: 42500 | K12: =(Fact_Ventas_Detalle[[#This Row],[Cantidad]]*Fact_Ventas_Detalle[[#This Row],[Precio Unitario]])-Fact_Ventas_Detalle[[#This Row],[Descuento Linea]] -> 807500
A13: 1 | B13: TXN-20260730-001 | C13: 1 | D13: PROD-107 | E13: Escritorio Ajustable | F13: Muebles | G13: 1 | H13: 240000 | I13: 150000 | J13: 24000 | K13: =(Fact_Ventas_Detalle[[#This Row],[Cantidad]]*Fact_Ventas_Detalle[[#This Row],[Precio Unitario]])-Fact_Ventas_Detalle[[#This Row],[Descuento Linea]] -> 216000
... A965: 101 | B965: TXN-20260729-040 | C965: 1 | D965: PROD-105 | E965: Auriculares Bluetooth | F965: Audio | G965: 1 | H965: 65000 | I965: 35000 | J965: 0 | K965: =(Fact_Ventas_Detalle[[#This Row],[Cantidad]]*Fact_Ventas_Detalle[[#This Row],[Precio Unitario]])-Fact_Ventas_Detalle[[#This Row],[Descuento Linea]] -> 65000

Sheet Fact_Ventas_Cabecera
A1: ID Transaccion | B1: Fecha Hora | C1: Sucursal | D1: Canal Venta | E1: ID Cliente | F1: Metodo Pago | G1: Vendedor
A2: TXN-20260727-002 | B2: 46230.426 | C2: SUC-003 E-Commerce | D2: E-Commerce | E2: CLI-4611 | F2: Efectivo | G2: SISTEMA-WEB
A3: TXN-20260727-004 | B3: 46230.407 | C3: SUC-003 E-Commerce | D3: E-Commerce | E3: CLI-6925 | F3: Tarjeta Débito | G3: SISTEMA-WEB
A4: TXN-20260727-005 | B4: 46230.836 | C4: SUC-003 E-Commerce | D4: E-Commerce | E4: CLI-8428 | F4: Transferencia | G4: SISTEMA-WEB
A5: TXN-20260727-008 | B5: 46230.665 | C5: SUC-003 E-Commerce | D5: E-Commerce | E5: CLI-9348 | F5: Efectivo | G5: SISTEMA-WEB
A6: TXN-20260727-011 | B6: 46230.483 | C6: SUC-003 E-Commerce | D6: E-Commerce | E6: CLI-2832 | F6: Transferencia | G6: SISTEMA-WEB
A7: TXN-20260727-015 | B7: 46230.524 | C7: SUC-003 E-Commerce | D7: E-Commerce | E7: CLI-2612 | F7: Tarjeta Crédito | G7: SISTEMA-WEB
A8: TXN-20260727-017 | B8: 46230.703 | C8: SUC-003 E-Commerce | D8: E-Commerce | E8: CLI-2528 | F8: Tarjeta Débito | G8: SISTEMA-WEB
A9: TXN-20260727-019 | B9: 46230.679 | C9: SUC-003 E-Commerce | D9: E-Commerce | E9: CLI-1931 | F9: Tarjeta Crédito | G9: SISTEMA-WEB
A10: TXN-20260727-021 | B10: 46230.818 | C10: SUC-003 E-Commerce | D10: E-Commerce | E10: CLI-8491 | F10: Transferencia | G10: SISTEMA-WEB
A11: TXN-20260727-022 | B11: 46230.417 | C11: SUC-003 E-Commerce | D11: E-Commerce | E11: CLI-9288 | F11: Transferencia | G11: SISTEMA-WEB
A12: TXN-20260728-003 | B12: 46231.829 | C12: SUC-003 E-Commerce | D12: E-Commerce | E12: CLI-7211 | F12: Tarjeta Débito | G12: SISTEMA-WEB
A13: TXN-20260728-005 | B13: 46231.564 | C13: SUC-003 E-Commerce | D13: E-Commerce | E13: CLI-8784 | F13: Tarjeta Crédito | G13: SISTEMA-WEB
... A398: TXN-20260807-029 | B398: 46241.507 | C398: SUC-001 Centro | D398: Tienda Física | E398: CLI-8192 | F398: Transferencia | G398: VEN-104 (Ana López)

Sheet Analisis
A2: Productos | B2: Total vendido por producto | E2: Productos | F2: Total vendio cantidad
A3: {=_xlfn.UNIQUE(Fact_Ventas_Detalle[Producto])} -> Monitor 27 UHD | B3: {=SUMPRODUCT((Fact_Ventas_Detalle[Producto]=Analisis!A3) * ((Fact_Ventas_Detalle[Cantidad] * Fact_Ventas_Detalle[Precio Unitario]) - Fact_Ventas_Detalle[Descuento Linea]))} -> 84644000 | E3: {=_xlfn.UNIQUE(Fact_Ventas_Detalle[Producto])} -> Monitor 27 UHD | F3: =SUMIF(Fact_Ventas_Detalle[Producto], Analisis!E3, Fact_Ventas_Detalle[Cantidad]) -> 315
A4: Auriculares Bluetooth | B4: {=SUMPRODUCT((Fact_Ventas_Detalle[Producto]=Analisis!A4) * ((Fact_Ventas_Detalle[Cantidad] * Fact_Ventas_Detalle[Precio Unitario]) - Fact_Ventas_Detalle[Descuento Linea]))} -> 14118000 | E4: Auriculares Bluetooth | F4: =SUMIF(Fact_Ventas_Detalle[Producto], Analisis!E4, Fact_Ventas_Detalle[Cantidad]) -> 226
A5: Webcam 4K Ultra | B5: {=SUMPRODUCT((Fact_Ventas_Detalle[Producto]=Analisis!A5) * ((Fact_Ventas_Detalle[Cantidad] * Fact_Ventas_Detalle[Precio Unitario]) - Fact_Ventas_Detalle[Descuento Linea]))} -> 16173750 | E5: Webcam 4K Ultra | F5: =SUMIF(Fact_Ventas_Detalle[Producto], Analisis!E5, Fact_Ventas_Detalle[Cantidad]) -> 224
A6: Teclado Mecánico RGB | B6: {=SUMPRODUCT((Fact_Ventas_Detalle[Producto]=Analisis!A6) * ((Fact_Ventas_Detalle[Cantidad] * Fact_Ventas_Detalle[Precio Unitario]) - Fact_Ventas_Detalle[Descuento Linea]))} -> 9441000 | E6: Teclado Mecánico RGB | F6: =SUMIF(Fact_Ventas_Detalle[Producto], Analisis!E6, Fact_Ventas_Detalle[Cantidad]) -> 218
A7: Escritorio Ajustable | B7: {=SUMPRODUCT((Fact_Ventas_Detalle[Producto]=Analisis!A7) * ((Fact_Ventas_Detalle[Cantidad] * Fact_Ventas_Detalle[Precio Unitario]) - Fact_Ventas_Detalle[Descuento Linea]))} -> 56112000 | E7: Escritorio Ajustable | F7: =SUMIF(Fact_Ventas_Detalle[Producto], Analisis!E7, Fact_Ventas_Detalle[Cantidad]) -> 241
A8: Notebook Pro 15 | B8: {=SUMPRODUCT((Fact_Ventas_Detalle[Producto]=Analisis!A8) * ((Fact_Ventas_Detalle[Cantidad] * Fact_Ventas_Detalle[Precio Unitario]) - Fact_Ventas_Detalle[Descuento Linea]))} -> 185427500 | E8: Notebook Pro 15 | F8: =SUMIF(Fact_Ventas_Detalle[Producto], Analisis!E8, Fact_Ventas_Detalle[Cantidad]) -> 227
A9: Silla Ergonómica Oficina | B9: {=SUMPRODUCT((Fact_Ventas_Detalle[Producto]=Analisis!A9) * ((Fact_Ventas_Detalle[Cantidad] * Fact_Ventas_Detalle[Precio Unitario]) - Fact_Ventas_Detalle[Descuento Linea]))} -> 44871750 | E9: Silla Ergonómica Oficina | F9: =SUMIF(Fact_Ventas_Detalle[Producto], Analisis!E9, Fact_Ventas_Detalle[Cantidad]) -> 252
A10: Mouse Inalámbrico | B10: {=SUMPRODUCT((Fact_Ventas_Detalle[Producto]=Analisis!A10) * ((Fact_Ventas_Detalle[Cantidad] * Fact_Ventas_Detalle[Precio Unitario]) - Fact_Ventas_Detalle[Descuento Linea]))} -> 6712500 | E10: Mouse Inalámbrico | F10: =SUMIF(Fact_Ventas_Detalle[Producto], Analisis!E10, Fact_Ventas_Detalle[Cantidad]) -> 281
B11: =SUM(B3:B10) -> 417500500
A13: Fecha | B13: Total facturados en el dia | E13: Canal de venta | F13: Total vendido
A14: {=_xlfn.UNIQUE(INT(Fact_Ventas_Cabecera[Fecha Hora]))} -> 46230 | B14: {=SUMPRODUCT((INT(VLOOKUP(Fact_Ventas_Detalle[ID Transaccion], Fact_Ventas_Cabecera[[ID Transaccion]:[Fecha Hora]], 2, FALSE))=Analisis!A14)*((Fact_Ventas_Detalle[Cantidad]*Fact_Ventas_Detalle[Precio Unitario])-Fact_Ventas_Detalle[Descuento Linea]))} -> 25867250 | E14: {=_xlfn.UNIQUE(Fact_Ventas_Cabecera[Canal Venta])} -> E-Commerce | F14: {=SUMPRODUCT((VLOOKUP(Fact_Ventas_Detalle[ID Transaccion],Fact_Ventas_Cabecera[[ID Transaccion]:[Canal Venta]],4,FALSE)=Analisis!E14)*(Fact_Ventas_Detalle[Total]))} -> 148847500
A15: 46231 | B15: {=SUMPRODUCT((INT(VLOOKUP(Fact_Ventas_Detalle[ID Transaccion], Fact_Ventas_Cabecera[[ID Transaccion]:[Fecha Hora]], 2, FALSE))=Analisis!A15)*((Fact_Ventas_Detalle[Cantidad]*Fact_Ventas_Detalle[Precio Unitario])-Fact_Ventas_Detalle[Descuento Linea]))} -> 40055500 | E15: Venta Telefónica | F15: {=SUMPRODUCT((VLOOKUP(Fact_Ventas_Detalle[ID Transaccion],Fact_Ventas_Cabecera[[ID Transaccion]:[Canal Venta]],4,FALSE)=Analisis!E15)*(Fact_Ventas_Detalle[Total]))} -> 149244750
A16: 46232 | B16: {=SUMPRODUCT((INT(VLOOKUP(Fact_Ventas_Detalle[ID Transaccion], Fact_Ventas_Cabecera[[ID Transaccion]:[Fecha Hora]], 2, FALSE))=Analisis!A16)*((Fact_Ventas_Detalle[Cantidad]*Fact_Ventas_Detalle[Precio Unitario])-Fact_Ventas_Detalle[Descuento Linea]))} -> 42682250 | E16: Tienda Física | F16: {=SUMPRODUCT((VLOOKUP(Fact_Ventas_Detalle[ID Transaccion],Fact_Ventas_Cabecera[[ID Transaccion]:[Canal Venta]],4,FALSE)=Analisis!E16)*(Fact_Ventas_Detalle[Total]))} -> 119408250
A17: 46233 | B17: {=SUMPRODUCT((INT(VLOOKUP(Fact_Ventas_Detalle[ID Transaccion], Fact_Ventas_Cabecera[[ID Transaccion]:[Fecha Hora]], 2, FALSE))=Analisis!A17)*((Fact_Ventas_Detalle[Cantidad]*Fact_Ventas_Detalle[Precio Unitario])-Fact_Ventas_Detalle[Descuento Linea]))} -> 33343250 | F17: =SUM(F14:F16) -> 417500500
A18: 46234 | B18: {=SUMPRODUCT((INT(VLOOKUP(Fact_Ventas_Detalle[ID Transaccion], Fact_Ventas_Cabecera[[ID Transaccion]:[Fecha Hora]], 2, FALSE))=Analisis!A18)*((Fact_Ventas_Detalle[Cantidad]*Fact_Ventas_Detalle[Precio Unitario])-Fact_Ventas_Detalle[Descuento Linea]))} -> 24447500
A19: 46235 | B19: {=SUMPRODUCT((INT(VLOOKUP(Fact_Ventas_Detalle[ID Transaccion], Fact_Ventas_Cabecera[[ID Transaccion]:[Fecha Hora]], 2, FALSE))=Analisis!A19)*((Fact_Ventas_Detalle[Cantidad]*Fact_Ventas_Detalle[Precio Unitario])-Fact_Ventas_Detalle[Descuento Linea]))} -> 46916250
A20: 46236 | B20: {=SUMPRODUCT((INT(VLOOKUP(Fact_Ventas_Detalle[ID Transaccion], Fact_Ventas_Cabecera[[ID Transaccion]:[Fecha Hora]], 2, FALSE))=Analisis!A20)*((Fact_Ventas_Detalle[Cantidad]*Fact_Ventas_Detalle[Precio Unitario])-Fact_Ventas_Detalle[Descuento Linea]))} -> 36266250
A21: 46237 | B21: {=SUMPRODUCT((INT(VLOOKUP(Fact_Ventas_Detalle[ID Transaccion], Fact_Ventas_Cabecera[[ID Transaccion]:[Fecha Hora]], 2, FALSE))=Analisis!A21)*((Fact_Ventas_Detalle[Cantidad]*Fact_Ventas_Detalle[Precio Unitario])-Fact_Ventas_Detalle[Descuento Linea]))} -> 30951500
A22: 46238 | B22: {=SUMPRODUCT((INT(VLOOKUP(Fact_Ventas_Detalle[ID Transaccion], Fact_Ventas_Cabecera[[ID Transaccion]:[Fecha Hora]], 2, FALSE))=Analisis!A22)*((Fact_Ventas_Detalle[Cantidad]*Fact_Ventas_Detalle[Precio Unitario])-Fact_Ventas_Detalle[Descuento Linea]))} -> 19981000
A23: 46239 | B23: {=SUMPRODUCT((INT(VLOOKUP(Fact_Ventas_Detalle[ID Transaccion], Fact_Ventas_Cabecera[[ID Transaccion]:[Fecha Hora]], 2, FALSE))=Analisis!A23)*((Fact_Ventas_Detalle[Cantidad]*Fact_Ventas_Detalle[Precio Unitario])-Fact_Ventas_Detalle[Descuento Linea]))} -> 43335500
A24: 46240 | B24: {=SUMPRODUCT((INT(VLOOKUP(Fact_Ventas_Detalle[ID Transaccion], Fact_Ventas_Cabecera[[ID Transaccion]:[Fecha Hora]], 2, FALSE))=Analisis!A24)*((Fact_Ventas_Detalle[Cantidad]*Fact_Ventas_Detalle[Precio Unitario])-Fact_Ventas_Detalle[Descuento Linea]))} -> 43461000
A25: 46241 | B25: {=SUMPRODUCT((INT(VLOOKUP(Fact_Ventas_Detalle[ID Transaccion], Fact_Ventas_Cabecera[[ID Transaccion]:[Fecha Hora]], 2, FALSE))=Analisis!A25)*((Fact_Ventas_Detalle[Cantidad]*Fact_Ventas_Detalle[Precio Unitario])-Fact_Ventas_Detalle[Descuento Linea]))} -> 30193250
B26: {=SUMPRODUCT((INT(VLOOKUP(Fact_Ventas_Detalle[ID Transaccion], Fact_Ventas_Cabecera[[ID Transaccion]:[Fecha Hora]], 2, FALSE))=Analisis!A26)*((Fact_Ventas_Detalle[Cantidad]*Fact_Ventas_Detalle[Precio Unitario])-Fact_Ventas_Detalle[Descuento Linea]))} -> 0
B27: {=SUMPRODUCT((INT(VLOOKUP(Fact_Ventas_Detalle[ID Transaccion], Fact_Ventas_Cabecera[[ID Transaccion]:[Fecha Hora]], 2, FALSE))=Analisis!A27)*((Fact_Ventas_Detalle[Cantidad]*Fact_Ventas_Detalle[Precio Unitario])-Fact_Ventas_Detalle[Descuento Linea]))} -> 0
B28: {=SUMPRODUCT((INT(VLOOKUP(Fact_Ventas_Detalle[ID Transaccion], Fact_Ventas_Cabecera[[ID Transaccion]:[Fecha Hora]], 2, FALSE))=Analisis!A28)*((Fact_Ventas_Detalle[Cantidad]*Fact_Ventas_Detalle[Precio Unitario])-Fact_Ventas_Detalle[Descuento Linea]))} -> 0
B29: {=SUMPRODUCT((INT(VLOOKUP(Fact_Ventas_Detalle[ID Transaccion], Fact_Ventas_Cabecera[[ID Transaccion]:[Fecha Hora]], 2, FALSE))=Analisis!A29)*((Fact_Ventas_Detalle[Cantidad]*Fact_Ventas_Detalle[Precio Unitario])-Fact_Ventas_Detalle[Descuento Linea]))} -> 0
B30: {=SUMPRODUCT((INT(VLOOKUP(Fact_Ventas_Detalle[ID Transaccion], Fact_Ventas_Cabecera[[ID Transaccion]:[Fecha Hora]], 2, FALSE))=Analisis!A30)*((Fact_Ventas_Detalle[Cantidad]*Fact_Ventas_Detalle[Precio Unitario])-Fact_Ventas_Detalle[Descuento Linea]))} -> 0
B31: {=SUMPRODUCT((INT(VLOOKUP(Fact_Ventas_Detalle[ID Transaccion], Fact_Ventas_Cabecera[[ID Transaccion]:[Fecha Hora]], 2, FALSE))=Analisis!A31)*((Fact_Ventas_Detalle[Cantidad]*Fact_Ventas_Detalle[Precio Unitario])-Fact_Ventas_Detalle[Descuento Linea]))} -> 0
